xstat/__init__.py
xstat/constants.py
xstat/django_stat.py
xstat/flask_stat.py
xstat/log.py
xstat/maple_stat.py
xstat/utils.py
xstat-0.2.6.dist-info/METADATA
xstat-0.2.6.dist-info/WHEEL
xstat-0.2.6.dist-info/top_level.txt
xstat-0.2.6.dist-info/RECORD
