Metadata-Version: 2.1
Name: xstat
Version: 0.2.6
Summary: make statsd work with flask, django, maple or other server
Home-page: https://github.com/dantezhu/xstat
Author: dantezhu
Author-email: dantezhu <dantezhu@qq.com>
License: MIT
Project-URL: Homepage, https://github.com/dantezhu/xstat
Requires-Dist: statsd
